<MaterialEntry>
	<Name>Forced Induction</Name>

	<Pages>
		<Page>
			<Paragraphs>
				<Title>
					<Text>{{MA.Forced_Induction.00.Title}}</Text>

				</Title>

				<Icon>
					<Name>Forced Induction</Name>

					<Alignment>Center</Alignment>

				</Icon>

				<Paragraph>
					<Text>{{MA.Forced_Induction.01.Paragraph}}</Text>

				</Paragraph>

				<Spacer/>

				<Paragraph>
					<Text>{{MA.Forced_Induction.02.Paragraph}}</Text>

				</Paragraph>

				<Spacer/>

				<Header><Text>{{MA.Forced_Induction.03.Header}}</Text>
</Header>

				<TwoColumnParagraph>
					<Left>{{MA.Forced_Induction.04.Left}}</Left>

					<Right>{{MA.Forced_Induction.05.Right}}</Right>

				</TwoColumnParagraph>

			</Paragraphs>

		</Page>
				
	</Pages>

</MaterialEntry>

