<MaterialEntry>
	<Key>GeothermalGeneratorPlacement</Key>
	<Pages>
		<Page>
			<Paragraphs>
				<Title>
					<Text>{{ index .Data "MA.Geothermal_Generator_Comp..00.Title" }}</Text>
				</Title>
				<Icon>
					<Name>Geothermal Generator Comp.</Name>
					<Alignment>Center</Alignment>
				</Icon>
				<Paragraph>
					<Text>{{ index .Data "MA.Geothermal_Generator_Comp..01.Paragraph" }}</Text>
				</Paragraph>
				<Spacer/>
				<Link>
					<Target>
						<Material>Heat Conducting Pipe</Material>
					</Target>
					<Text>Heat Conducting Pipe</Text>
				</Link>
			</Paragraphs>
		</Page>
				
	</Pages>
</MaterialEntry>
