<MaterialEntry>
	<Name>Macerator</Name>

	<Pages>
		<Page>
			<Paragraphs>
				<Title>
					<Text>{{MA.Macerator.00.Title}}</Text>

				</Title>

				<Icon>
					<Name>Macerator</Name>

					<Alignment>Center</Alignment>

				</Icon>

				<Paragraph>
					<Text>{{MA.Macerator.01.Paragraph}}</Text>

				</Paragraph>

				<Spacer/>

				<TwoColumnParagraph>
					<Left>{{MA.Macerator.02.Left}}</Left>

					<Right>{{MA.Macerator.03.Right}}</Right>

				</TwoColumnParagraph>

				<Spacer/>

				<Spacer/>

				<Header>
					<Text>{{MA.Macerator.04.Header}}</Text>

				</Header>

				<Paragraph><Text>{{MA.Macerator.05.Paragraph}}</Text>
</Paragraph>

			</Paragraphs>

		</Page>
				
	</Pages>

</MaterialEntry>


